ghswitch/__init__.py
ghswitch/account.py
ghswitch/cli.py
ghswitch/config.py
ghswitch/platforms/__init__.py
ghswitch/platforms/base.py
ghswitch/platforms/macos.py
ghswitch/platforms/windows.py
ghswitch-0.1.1.dist-info/licenses/LICENSE
ghswitch-0.1.1.dist-info/METADATA
ghswitch-0.1.1.dist-info/WHEEL
ghswitch-0.1.1.dist-info/entry_points.txt
ghswitch-0.1.1.dist-info/top_level.txt
ghswitch-0.1.1.dist-info/RECORD
