Metadata-Version: 2.4
Name: ghswitch
Version: 0.1.1
Summary: A tool for managing multiple GitHub accounts on a single device
Author-email: GitHub Account Manager <example@example.com>
License-Expression: MIT
Project-URL: Homepage, https://github.com/yourusername/ghswitch
Project-URL: Bug Tracker, https://github.com/yourusername/ghswitch/issues
Keywords: github,git,account,management
Classifier: Development Status :: 4 - Beta
Classifier: Intended Audience :: Developers
Classifier: Topic :: Software Development :: Version Control :: Git
Classifier: Programming Language :: Python :: 3
Classifier: Programming Language :: Python :: 3.6
Classifier: Programming Language :: Python :: 3.7
Classifier: Programming Language :: Python :: 3.8
Classifier: Programming Language :: Python :: 3.9
Classifier: Programming Language :: Python :: 3.10
Classifier: Operating System :: OS Independent
Requires-Python: >=3.6
License-File: LICENSE
Requires-Dist: click>=8.0.0
Requires-Dist: pyyaml>=6.0
Requires-Dist: gitpython>=3.1.0
Dynamic: license-file
